CHANGES.txt
MANIFEST.in
README.txt
setup.cfg
setup.py
TracGoogleAppsAuthPlugin.egg-info/PKG-INFO
TracGoogleAppsAuthPlugin.egg-info/SOURCES.txt
TracGoogleAppsAuthPlugin.egg-info/dependency_links.txt
TracGoogleAppsAuthPlugin.egg-info/entry_points.txt
TracGoogleAppsAuthPlugin.egg-info/requires.txt
TracGoogleAppsAuthPlugin.egg-info/top_level.txt
googleappsauth/__init__.py
googleappsauth/plugin.py
googleappsauth/locale/messages.pot
googleappsauth/locale/en_US/LC_MESSAGES/googleappsauth.mo
googleappsauth/locale/en_US/LC_MESSAGES/googleappsauth.po