Metadata-Version: 1.0
Name: TracGoogleAppsAuthPlugin
Version: 0.3.1
Summary: Trac authentication plugin for integration with hosted Google Apps domain
Home-page: http://code.google.com/p/tracgoogleappsauthplugin/
Author: David A. Riggs
Author-email: david.riggs@createtank.com
License: UNKNOWN
Download-URL: http://code.google.com/p/tracgoogleappsauthplugin/
Platform: UNKNOWN
Classifier: Development Status :: 3 - Alpha
Classifier: Environment :: Plugins
Classifier: Framework :: Trac
Classifier: Intended Audience :: System Administrators
Classifier: License :: OSI Approved :: GNU General Public License (GPL)
Classifier: Natural Language :: English
Classifier: Operating System :: OS Independent
Classifier: Programming Language :: Python
Classifier: Programming Language :: Python :: 2
Classifier: Programming Language :: Python :: 2.5
Classifier: Topic :: System :: Systems Administration :: Authentication/Directory
